crypto_currency/__init__.py
crypto_currency/coin_market_cap.py
crypto_currency/crypto_compare.py
crypto_currency/exchange.py
crypto_currency/utils.py
crypto_currency-0.1.0.dist-info/METADATA
crypto_currency-0.1.0.dist-info/RECORD
crypto_currency-0.1.0.dist-info/WHEEL
crypto_currency-0.1.0.dist-info/top_level.txt
