Metadata-Version: 2.1
Name: crypto-currency
Version: 0.1.0
Summary: Some crypto currency SDKs
Home-page: https://github.com/Vaayne/crypto_currency
Author: Vaayne
Author-email: lyishaou@gmail.com
License: MIT
Platform: UNKNOWN
Classifier: License :: OSI Approved :: MIT License
Classifier: Programming Language :: Python
Classifier: Programming Language :: Python :: 3
Classifier: Programming Language :: Python :: 3.6
Classifier: Programming Language :: Python :: Implementation :: CPython
Classifier: Programming Language :: Python :: Implementation :: PyPy
Requires-Python: >=3.6.0
Requires-Dist: twine
Requires-Dist: pandas
Requires-Dist: ccxt
